{"last_cleanup":1713709725,"data":{"\/home\/comodino":{"filetype":"","visit_log":[{"elapsed_time_sec":0,"keystrokes":0,"entry":1713709961}],"git_project_name":""},"\/home\/comodino\/.ssh\/known_hosts":{"filetype":"","visit_log":[{"elapsed_time_sec":6,"exit":1713712242,"keystrokes":22,"entry":1713712236}],"git_project_name":""},"\/home\/comodino\/.dotfiles\/scripts\/.local\/scripts\/waybar_spotify.sh":{"filetype":"sh","visit_log":[{"elapsed_time_sec":86,"entry":1713710308,"keystrokes":439,"exit":1713710394},{"elapsed_time_sec":81,"entry":1713710449,"keystrokes":401,"exit":1713710530},{"elapsed_time_sec":11,"entry":1713710542,"keystrokes":50,"exit":1713710553},{"elapsed_time_sec":8,"entry":1713710729,"keystrokes":29,"exit":1713710737},{"elapsed_time_sec":65,"entry":1713710851,"keystrokes":296,"exit":1713710916},{"elapsed_time_sec":59,"entry":1713710926,"keystrokes":113,"exit":1713710985},{"elapsed_time_sec":48,"entry":1713711004,"keystrokes":217,"exit":1713711052},{"elapsed_time_sec":100,"entry":1713711398,"keystrokes":353,"exit":1713711498}],"git_project_name":""},"\/home\/comodino\/.dotfiles\/systemd\/.config\/systemd\/user\/waybar.service":{"filetype":"systemd","visit_log":[{"elapsed_time_sec":11,"entry":1713709725,"keystrokes":41,"exit":1713709736}],"git_project_name":""},"\/home\/comodino\/.dotfiles\/waybar\/.config\/waybar\/config.jsonc":{"filetype":"jsonc","visit_log":[{"elapsed_time_sec":22,"entry":1713710212,"keystrokes":125,"exit":1713710234},{"elapsed_time_sec":11,"entry":1713710260,"keystrokes":79,"exit":1713710271},{"elapsed_time_sec":25,"entry":1713711070,"keystrokes":146,"exit":1713711095},{"elapsed_time_sec":184,"entry":1713711534,"keystrokes":372,"exit":1713711718},{"elapsed_time_sec":9,"entry":1713711761,"keystrokes":21,"exit":1713711770},{"elapsed_time_sec":16,"entry":1713711866,"keystrokes":55,"exit":1713711882}],"git_project_name":""},"\/home\/comodino\/.dotfiles":{"visit_log":[{"elapsed_time_sec":0,"keystrokes":0,"entry":1713712613}],"filetype":"","git_project_name":""}}}